elma_verifier/__init__.py
elma_verifier/verifier.py
elma_verifier-0.0.6.dist-info/LICENSE
elma_verifier-0.0.6.dist-info/METADATA
elma_verifier-0.0.6.dist-info/WHEEL
elma_verifier-0.0.6.dist-info/top_level.txt
elma_verifier-0.0.6.dist-info/RECORD
