Metadata-Version: 2.1
Name: elma-verifier
Version: 0.0.6
Summary: A package for validating Norwegian organization numbers and checking whether the organization number is registered in the ELMA-registry.
Author-email: Mathias Mjømen <mathiassmjomen@gmail.com>
Project-URL: Homepage, https://github.com/MDiddle/elma-verifier
Project-URL: Bug Tracker, https://github.com/MDiddle/elma-verifier/issues
Classifier: Programming Language :: Python :: 3
Classifier: License :: OSI Approved :: MIT License
Classifier: Operating System :: OS Independent
Requires-Python: >=3.7
License-File: LICENSE
Requires-Dist: selenium >=4.6
